wangls/__init__.py
wangls/cli.py
wangls/wangls.py
wangls-0.1.6.dist-info/LICENSE
wangls-0.1.6.dist-info/METADATA
wangls-0.1.6.dist-info/WHEEL
wangls-0.1.6.dist-info/entry_points.txt
wangls-0.1.6.dist-info/top_level.txt
wangls-0.1.6.dist-info/RECORD
