Metadata-Version: 2.1
Name: wangls
Version: 0.1.6
Summary: A command line tool that gives you the IPs of the devices connected to the same network segment.
Home-page: https://github.com/ally-ahmed/wangls
Author: Ahmed Ali
Author-email: norbixin@live.com
License: MIT license
Keywords: wangls
Platform: UNKNOWN
Classifier: Development Status :: 2 - Pre-Alpha
Classifier: Intended Audience :: Developers
Classifier: License :: OSI Approved :: MIT License
Classifier: Natural Language :: English
Classifier: Programming Language :: Python :: 3
Classifier: Programming Language :: Python :: 3.5
Classifier: Programming Language :: Python :: 3.6
Classifier: Programming Language :: Python :: 3.7
Classifier: Programming Language :: Python :: 3.8
Requires-Python: >=3.5
Requires-Dist: Click (>=7.0)
Requires-Dist: terminaltables
Requires-Dist: halo
